icc/__init__.py
icc/_version.py
icc/icc.py
icc-0.1.1.dist-info/LICENSE
icc-0.1.1.dist-info/METADATA
icc-0.1.1.dist-info/WHEEL
icc-0.1.1.dist-info/top_level.txt
icc-0.1.1.dist-info/RECORD
